forgepro/__init__.py
forgepro/default_settings.py
forge_pro-0.2.0.dist-info/LICENSE
forge_pro-0.2.0.dist-info/METADATA
forge_pro-0.2.0.dist-info/WHEEL
forge_pro-0.2.0.dist-info/RECORD
