Metadata-Version: 2.1
Name: forge-pro
Version: 0.2.0
Summary: 
Author: Dave Gaeddert
Author-email: dave.gaeddert@dropseed.dev
Requires-Python: >=3.8,<4.0
Classifier: Programming Language :: Python :: 3
Classifier: Programming Language :: Python :: 3.8
Classifier: Programming Language :: Python :: 3.9
Classifier: Programming Language :: Python :: 3.10
Classifier: Programming Language :: Python :: 3.11
Classifier: Programming Language :: Python :: 3.12
Classifier: Programming Language :: Python :: 3.13
Requires-Dist: forge-googleanalytics (<1.0.0)
Requires-Dist: forge-impersonate (<1.0.0)
Requires-Dist: forge-querystats (<1.0.0)
Requires-Dist: forge-requestlog (<1.0.0)
Requires-Dist: forge-sentry (<1.0.0)
Requires-Dist: forge-stafftoolbar (<1.0.0)
Requires-Dist: forge-stripe (<1.0.0)
